logpurge/__init__.py
logpurge-0.3.dist-info/LICENSE.md
logpurge-0.3.dist-info/METADATA
logpurge-0.3.dist-info/WHEEL
logpurge-0.3.dist-info/entry_points.txt
logpurge-0.3.dist-info/top_level.txt
logpurge-0.3.dist-info/RECORD
