Metadata-Version: 2.1
Name: logpurge
Version: 0.3
Summary: Logarithmically purge data
Home-page: https://github.com/nijotz/logpurge
Author: Nick Tzaperas
Author-email: nick@nijotz.com
License: UNKNOWN
Platform: UNKNOWN
